{
  "moves": {
    "1": {
      "id": 1,
      "name": "Impactrueno",
      "power": "40",
      "powerPoint": 30,
      "precision": 100,
      "type": "Eléctrico",
      "effect": "Puede paralizar al objetivo."
    },
    "2": {
      "id": 2,
      "name": "Ascuas",
      "power": "40",
      "powerPoint": 25,
      "precision": 100,
      "type": "Fuego",
      "effect": "Puede quemar al objetivo."
    },
    "3": {
      "id": 3,
      "name": "Placaje",
      "power": "40",
      "powerPoint": 35,
      "precision": 100,
      "type": "Normal",
      "effect": "Un ataque físico básico."
    },
    "4": {
      "id": 4,
      "name": "Látigo Cepa",
      "power": "45",
      "powerPoint": 25,
      "precision": 100,
      "type": "Planta",
      "effect": "Un ataque físico con látigos de plantas."
    },
    "5": {
      "id": 5,
      "name": "Burbuja",
      "power": "40",
      "powerPoint": 30,
      "precision": 100,
      "type": "Agua",
      "effect": "Puede reducir la velocidad del objetivo."
    }
  },
  "pokemons": {
    "1": {
      "id": 1,
      "name": "Pikachu",
      "image": "https://raw.githubusercontent.com/PokeAPI/sprites/master/sprites/pokemon/25.png",
      "moves": [
        1,
        3
      ]
    },
    "2": {
      "id": 2,
      "name": "Charmander",
      "image": "https://raw.githubusercontent.com/PokeAPI/sprites/master/sprites/pokemon/4.png",
      "moves": [
        2,
        3
      ]
    },
    "3": {
      "id": 3,
      "name": "Bulbasaur",
      "image": "https://raw.githubusercontent.com/PokeAPI/sprites/master/sprites/pokemon/1.png",
      "moves": [
        4,
        3
      ]
    },
    "4": {
      "id": 4,
      "name": "Squirtle",
      "image": "https://raw.githubusercontent.com/PokeAPI/sprites/master/sprites/pokemon/7.png",
      "moves": [
        5,
        3
      ]
    },
    "5": {
      "id": 5,
      "name": "Eevee",
      "image": "https://raw.githubusercontent.com/PokeAPI/sprites/master/sprites/pokemon/133.png",
      "moves": [
        3
      ]
    }
  }
}
